friendly_web_face/__init__.py
friendly_web_face/ip_utils.py
friendly_web_face/translation.py
friendly_web_face/web_content.py
friendly_web_face-0.1.1.dist-info/licenses/LICENSE
friendly_web_face-0.1.1.dist-info/METADATA
friendly_web_face-0.1.1.dist-info/WHEEL
friendly_web_face-0.1.1.dist-info/top_level.txt
friendly_web_face-0.1.1.dist-info/RECORD
