Metadata-Version: 2.4
Name: friendly-web-face
Version: 0.1.1
Summary: Библиотека для перевода создания дружественного интерфейса
Home-page: https://github.com/MaXikme/friendly_web_face
Author: Максим
License-File: LICENSE
Requires-Dist: requests
Requires-Dist: beautifulsoup4
Requires-Dist: googletrans==4.0.0-rc1
Dynamic: author
Dynamic: description
Dynamic: description-content-type
Dynamic: home-page
Dynamic: license-file
Dynamic: requires-dist
Dynamic: summary
